[{"__type__":"cc.ImageAsset","content":{"fmt":"0","w":106,"h":887}},{"__type__":"cc.SpriteFrame","content":{"image":"17c8771ea","name":"theme5-row_bg","rect":{"x":3,"y":3,"width":100,"height":100},"offset":{"x":0,"y":0},"originalSize":{"width":100,"height":100},"rotated":false,"capInsets":[0,0,0,0]}},{"__type__":"cc.SpriteFrame","content":{"image":"17c8771ea","name":"theme-lock","rect":{"x":3,"y":745,"width":88,"height":112},"offset":{"x":0,"y":0},"originalSize":{"width":96,"height":122},"rotated":false,"capInsets":[0,0,0,0]}},{"__type__":"cc.SpriteFrame","content":{"image":"17c8771ea","name":"theme2-cube_bg","rect":{"x":3,"y":109,"width":100,"height":100},"offset":{"x":0,"y":0},"originalSize":{"width":100,"height":100},"rotated":false,"capInsets":[0,0,0,0]}},{"__type__":"cc.SpriteFrame","content":{"image":"17c8771ea","name":"theme4-star_bg","rect":{"x":3,"y":215,"width":100,"height":100},"offset":{"x":0,"y":0},"originalSize":{"width":100,"height":100},"rotated":false,"capInsets":[0,0,0,0]}},{"__type__":"cc.SpriteFrame","content":{"image":"17c8771ea","name":"theneChangeBtn","rect":{"x":3,"y":321,"width":100,"height":100},"offset":{"x":0,"y":0},"originalSize":{"width":100,"height":100},"rotated":false,"capInsets":[0,0,0,0]}},{"__type__":"cc.SpriteFrame","content":{"image":"17c8771ea","name":"theme3-grid1_bg","rect":{"x":3,"y":427,"width":100,"height":100},"offset":{"x":0,"y":0},"originalSize":{"width":100,"height":100},"rotated":false,"capInsets":[0,0,0,0]}},{"__type__":"cc.SpriteFrame","content":{"image":"17c8771ea","name":"theme-now","rect":{"x":3,"y":863,"width":21,"height":21},"offset":{"x":0,"y":0},"originalSize":{"width":21,"height":21},"rotated":false,"capInsets":[9,9,9,9]}},{"__type__":"cc.SpriteFrame","content":{"image":"17c8771ea","name":"theme1-original","rect":{"x":3,"y":533,"width":100,"height":100},"offset":{"x":0,"y":0},"originalSize":{"width":100,"height":100},"rotated":false,"capInsets":[0,0,0,0]}},{"__type__":"cc.SpriteFrame","content":{"image":"17c8771ea","name":"theme6-column_bg","rect":{"x":3,"y":639,"width":100,"height":100},"offset":{"x":0,"y":0},"originalSize":{"width":100,"height":100},"rotated":false,"capInsets":[0,0,0,0]}}]
